LICENSE
README.md
theoneapisdk/__init__.py
theoneapisdk/__metadata__.py
theoneapisdk/_config.py
theoneapisdk/_utils.py
theoneapisdk/books.py
theoneapisdk/chapters.py
theoneapisdk/characters.py
theoneapisdk/exceptions.py
theoneapisdk/movies.py
theoneapisdk/quotes.py
the_one_api_sdk-0.1.0.dist-info/LICENSE
the_one_api_sdk-0.1.0.dist-info/WHEEL
the_one_api_sdk-0.1.0.dist-info/METADATA
the_one_api_sdk-0.1.0.dist-info/RECORD
