Metadata-Version: 2.1
Name: the-one-api-sdk
Version: 0.1.0
Summary: the_one_api_sdk is a Python client implemented most of the APIs for the-one-api.dev.
Keywords: the_one_api
Author: Yair Rozenberg
Author-email: yairrose@gmail.com
Requires-Python: >=3.7.1,<3.11
Classifier: Programming Language :: Python :: 3
Classifier: Programming Language :: Python :: 3.8
Classifier: Programming Language :: Python :: 3.9
Classifier: Programming Language :: Python :: 3.10
Classifier: Programming Language :: Python :: 3.10
Classifier: Programming Language :: Python :: 3.7
Classifier: Programming Language :: Python :: 3.8
Classifier: Programming Language :: Python :: 3.9
Requires-Dist: requests (>=2.28.1,<3.0.0)
